stay_online/__init__.py
stay_online/cli.py
stay_online/constants.py
stay_online/stay_online.py
stay_online/word_file.txt
stay_online-0.2.0.dist-info/METADATA
stay_online-0.2.0.dist-info/WHEEL
stay_online-0.2.0.dist-info/entry_points.txt
stay_online-0.2.0.dist-info/licenses/LICENSE
stay_online-0.2.0.dist-info/RECORD
