Metadata-Version: 2.4
Name: stay_online
Version: 0.2.0
Summary: Simulate fake mouse and keyboard actions to fake staying online
Project-URL: Homepage, https://github.com/Chiaope/stay_online
Author: Chiaope
License-File: LICENSE
Classifier: License :: OSI Approved :: MIT License
Classifier: Operating System :: OS Independent
Classifier: Programming Language :: Python :: 3
Requires-Python: >=3.8
Requires-Dist: pyautogui
Requires-Dist: pynput
